{"id":1735313612001,"title":"Task 6: Expand reporting and analytics capabilities.","description":"Generate real-time reports for task progress (velocity, lead time) and commit statistics.","status":"Product Backlog","assignee":"Larry","files":[{"author":{"name":"jrheisler","email":"jrheisler@yahoo.com","date":"2025-01-06T23:37:24Z"},"committer":{"name":"jrheisler","email":"jrheisler@yahoo.com","date":"2025-01-06T23:37:24Z"},"message":"Version .260\n\nCard ID:  1735313574581\nCard ID: 1735313597168\nCard ID: 1735313612001\nCard ID: 1735313609008","tree":{"sha":"a56bd35d36e7e152736e6a5b6c3248f8de1f1d21","url":"https://api.github.com/repos/jrheisler/cm2git/git/trees/a56bd35d36e7e152736e6a5b6c3248f8de1f1d21"},"url":"https://api.github.com/repos/jrheisler/cm2git/git/commits/7df334ad82eb3f99bad7b9f161b85a3f4bccd74c","commentCount":0,"verification":{"verified":false,"reason":"unsigned","signature":"","payload":""},"sha":"7df334ad82eb3f99bad7b9f161b85a3f4bccd74c"}],"pulls":[],"branches":[],"sha":"7df334ad82eb3f99bad7b9f161b85a3f4bccd74c","dates":[{"date":"2024-12-27T07:34:12.001","status":"Product Backlog"}],"need_date":"2025-03-12T00:00:00.000","blocked":false,"blockReason":"Created text is a text written by a non-native speaker for a non-native audience to achieve specific curricular goals. Created texts have been a common feature in language classrooms, but educators are increasingly using more authentic texts in their teaching. ","isModified":true}